grafanacode/__init__.py
grafanacode/c_colors.py
grafanacode/c_units.py
grafanacode/funcs.py
grafanacode/funcs_api.py
grafanacode/examples/__init__.py
grafanacode/examples/backup.py
grafanacode/examples/extract.py
grafanacode/examples/gen_dash1.py
grafanacode/examples/gen_dash2.py
grafanacode/plugins/__init__.py
grafanacode/plugins/dashboard_base.py
grafanacode/plugins/panel_barchart.py
grafanacode/plugins/panel_bargauge.py
grafanacode/plugins/panel_base.py
grafanacode/plugins/panel_boomtable.py
grafanacode/plugins/panel_carpetplot.py
grafanacode/plugins/panel_dashboardlist.py
grafanacode/plugins/panel_dynamicimage.py
grafanacode/plugins/panel_flant_statusmap.py
grafanacode/plugins/panel_gauge.py
grafanacode/plugins/panel_geomap.py
grafanacode/plugins/panel_heatmap.py
grafanacode/plugins/panel_histogram.py
grafanacode/plugins/panel_logs.py
grafanacode/plugins/panel_news.py
grafanacode/plugins/panel_piechart.py
grafanacode/plugins/panel_plotly.py
grafanacode/plugins/panel_plotly_windrose.py
grafanacode/plugins/panel_row.py
grafanacode/plugins/panel_stat.py
grafanacode/plugins/panel_statetimeline.py
grafanacode/plugins/panel_table.py
grafanacode/plugins/panel_text.py
grafanacode/plugins/panel_timeseries.py
grafanacode/plugins/target_base.py
grafanacode/plugins/target_influxdb.py
grafanacode/plugins/target_prometheus.py
grafanacode/tests/__init__.py
grafanacode/tests/test_funcs.py
grafanacode-0.5.7.dist-info/LICENSE
grafanacode-0.5.7.dist-info/METADATA
grafanacode-0.5.7.dist-info/WHEEL
grafanacode-0.5.7.dist-info/top_level.txt
grafanacode-0.5.7.dist-info/RECORD
