Metadata-Version: 2.1
Name: grafanacode
Version: 0.5.7
Summary: Grafana dashboards as Python code
Author-email: DOSprojects <mail@domain.com>
License: Apache License
Project-URL: homepage, https://github.com/DOSprojects/grafanacode.git
Project-URL: documentation, https://grafanacode.readthedocs.io/en/latest/doc_module/grafanacode.html
Project-URL: repository, https://github.com/DOSprojects/grafanacode.git
Project-URL: changelog, https://github.com/DOSprojects/grafanacode/blob/main/CHANGELOG.rst
Keywords: Grafana,Python,code
Classifier: Development Status :: 3 - Alpha
Classifier: Environment :: Console
Classifier: License :: OSI Approved :: Apache Software License
Classifier: Operating System :: OS Independent
Classifier: Programming Language :: Python
Classifier: Programming Language :: Python :: 3.7
Classifier: Programming Language :: Python :: 3.8
Classifier: Programming Language :: Python :: 3.9
Classifier: Topic :: Software Development :: Libraries :: Python Modules
Classifier: Topic :: System :: Monitoring
Requires-Python: >=3.7
License-File: LICENSE
Requires-Dist: attrs (>=21.3.0)
Requires-Dist: requests
Provides-Extra: dev
Requires-Dist: pylint ; extra == 'dev'
Requires-Dist: sphinx ; extra == 'dev'
Provides-Extra: doc
Requires-Dist: sphinx ; extra == 'doc'
Provides-Extra: test
Requires-Dist: pytest (>5.0.0) ; extra == 'test'
